Workbook

Sheet Raw_Data
A1: Order_ID | B1: Order_Date | C1: Region | D1: City | E1: Category | F1: Product | G1: Customer_Segment | H1: Sales_Channel | I1: Quantity | J1: Unit_Price | K1: Discount_Rate | L1: Sales_Revenue | M1: Cost | N1: Profit
A2: ORD-0782 | B2: 45658 | C2: West | D2: Pune | E2: Home & Kitchen | F2: Coffee Maker | G2: Small Business | H2: Marketplace | I2: 11 | J2: 85.7 | K2: 0 | L2: 942.7 | M2: 469.51 | N2: 473.19
A3: ORD-0024 | B3: 45659 | C3: West | D3: Pune | E3: Home & Kitchen | F3: Coffee Maker | G3: Consumer | H3: Online | I3: 8 | J3: 68.39 | K3: 0.15 | L3: 465.05 | M3: 371.25 | N3: 93.8
A4: ORD-0537 | B4: 45659 | C4: North | D4: Delhi | E4: Furniture | F4: Office Chair | G4: Corporate | H4: In-Store | I4: 8 | J4: 148.5 | K4: 0.1 | L4: 1069.2 | M4: 763.94 | N4: 305.26
A5: ORD-0075 | B5: 45659 | C5: East | D5: Guwahati | E5: Home & Kitchen | F5: Lunch Box | G5: Corporate | H5: In-Store | I5: 12 | J5: 21.16 | K5: 0.05 | L5: 241.22 | M5: 124.37 | N5: 116.85
A6: ORD-0769 | B6: 45659 | C6: East | D6: Bhubaneswar | E6: Technology | F6: Headphones | G6: Corporate | H6: In-Store | I6: 2 | J6: 63.51 | K6: 0.1 | L6: 114.32 | M6: 79.31 | N6: 35.01
A7: ORD-0295 | B7: 45659 | C7: South | D7: Hyderabad | E7: Technology | F7: Wireless Mouse | G7: Consumer | H7: Online | I7: 4 | J7: 15.59 | K7: 0.05 | L7: 59.24 | M7: 37.1 | N7: 22.14
A8: ORD-0331 | B8: 45659 | C8: North | D8: Delhi | E8: Home & Kitchen | F8: Water Bottle | G8: Consumer | H8: Online | I8: 5 | J8: 18.21 | K8: 0.15 | L8: 77.39 | M8: 56.82 | N8: 20.57
A9: ORD-0735 | B9: 45660 | C9: West | D9: Ahmedabad | E9: Home & Kitchen | F9: Water Bottle | G9: Corporate | H9: Marketplace | I9: 1 | J9: 14.56 | K9: 0.1 | L9: 13.1 | M9: 9 | N9: 4.1
A10: ORD-0241 | B10: 45660 | C10: South | D10: Hyderabad | E10: Furniture | F10: Standing Desk | G10: Small Business | H10: In-Store | I10: 6 | J10: 290.28 | K10: 0 | L10: 1741.68 | M10: 905.24 | N10: 836.44
A11: ORD-0666 | B11: 45660 | C11: South | D11: Bengaluru | E11: Technology | F11: Keyboard | G11: Small Business | H11: Marketplace | I11: 9 | J11: 36.73 | K11: 0.1 | L11: 297.51 | M11: 195.02 | N11: 102.49
A12: ORD-0259 | B12: 45660 | C12: South | D12: Bengaluru | E12: Office Supplies | F12: Pen Set | G12: Small Business | H12: In-Store | I12: 5 | J12: 8.91 | K12: 0 | L12: 44.55 | M12: 29.1 | N12: 15.45
A13: ORD-0361 | B13: 45660 | C13: South | D13: Bengaluru | E13: Home & Kitchen | F13: Coffee Maker | G13: Small Business | H13: Online | I13: 4 | J13: 80.38 | K13: 0 | L13: 321.52 | M13: 209.92 | N13: 111.6
... A1001: ORD-0536 | B1001: 46022 | C1001: South | D1001: Bengaluru | E1001: Technology | F1001: USB Hub | G1001: Consumer | H1001: Online | I1001: 5 | J1001: 23 | K1001: 0.1 | L1001: 103.5 | M1001: 65.16 | N1001: 38.34

Sheet Working_Analysis
A1: Order_ID | B1: Order_Date | C1: Region | D1: City | E1: Category | F1: Product | G1: Customer_Segment | H1: Sales_Channel | I1: Quantity | J1: Unit_Price | K1: Discount_Rate | L1: Sales_Revenue | M1: Cost | N1: Profit | O1: Month | P1: Profit_Margin | Q1: Average_Order_Value
A2: =Raw_Data!A2 -> ORD-0782 | B2: =Raw_Data!B2 -> 45658 | C2: =Raw_Data!C2 -> West | D2: =Raw_Data!D2 -> Pune | E2: =Raw_Data!E2 -> Home & Kitchen | F2: =Raw_Data!F2 -> Coffee Maker | G2: =Raw_Data!G2 -> Small Business | H2: =Raw_Data!H2 -> Marketplace | ... N2: =Raw_Data!N2 -> 473.19 | O2: =TEXT(B2,"yyyy-mm") -> 2025-01 | P2: =IFERROR(N2/L2,0) -> 0.50195184 | Q2: =IFERROR(L2,0) -> 942.7
A3: =Raw_Data!A3 -> ORD-0024 | B3: =Raw_Data!B3 -> 45659 | C3: =Raw_Data!C3 -> West | D3: =Raw_Data!D3 -> Pune | E3: =Raw_Data!E3 -> Home & Kitchen | F3: =Raw_Data!F3 -> Coffee Maker | G3: =Raw_Data!G3 -> Consumer | H3: =Raw_Data!H3 -> Online | ... N3: =Raw_Data!N3 -> 93.8 | O3: =TEXT(B3,"yyyy-mm") -> 2025-01 | P3: =IFERROR(N3/L3,0) -> 0.20169874 | Q3: =IFERROR(L3,0) -> 465.05
A4: =Raw_Data!A4 -> ORD-0537 | B4: =Raw_Data!B4 -> 45659 | C4: =Raw_Data!C4 -> North | D4: =Raw_Data!D4 -> Delhi | E4: =Raw_Data!E4 -> Furniture | F4: =Raw_Data!F4 -> Office Chair | G4: =Raw_Data!G4 -> Corporate | H4: =Raw_Data!H4 -> In-Store | ... N4: =Raw_Data!N4 -> 305.26 | O4: =TEXT(B4,"yyyy-mm") -> 2025-01 | P4: =IFERROR(N4/L4,0) -> 0.28550318 | Q4: =IFERROR(L4,0) -> 1069.2
A5: =Raw_Data!A5 -> ORD-0075 | B5: =Raw_Data!B5 -> 45659 | C5: =Raw_Data!C5 -> East | D5: =Raw_Data!D5 -> Guwahati | E5: =Raw_Data!E5 -> Home & Kitchen | F5: =Raw_Data!F5 -> Lunch Box | G5: =Raw_Data!G5 -> Corporate | H5: =Raw_Data!H5 -> In-Store | ... N5: =Raw_Data!N5 -> 116.85 | O5: =TEXT(B5,"yyyy-mm") -> 2025-01 | P5: =IFERROR(N5/L5,0) -> 0.48441257 | Q5: =IFERROR(L5,0) -> 241.22
A6: =Raw_Data!A6 -> ORD-0769 | B6: =Raw_Data!B6 -> 45659 | C6: =Raw_Data!C6 -> East | D6: =Raw_Data!D6 -> Bhubaneswar | E6: =Raw_Data!E6 -> Technology | F6: =Raw_Data!F6 -> Headphones | G6: =Raw_Data!G6 -> Corporate | H6: =Raw_Data!H6 -> In-Store | ... N6: =Raw_Data!N6 -> 35.01 | O6: =TEXT(B6,"yyyy-mm") -> 2025-01 | P6: =IFERROR(N6/L6,0) -> 0.30624563 | Q6: =IFERROR(L6,0) -> 114.32
A7: =Raw_Data!A7 -> ORD-0295 | B7: =Raw_Data!B7 -> 45659 | C7: =Raw_Data!C7 -> South | D7: =Raw_Data!D7 -> Hyderabad | E7: =Raw_Data!E7 -> Technology | F7: =Raw_Data!F7 -> Wireless Mouse | G7: =Raw_Data!G7 -> Consumer | H7: =Raw_Data!H7 -> Online | ... N7: =Raw_Data!N7 -> 22.14 | O7: =TEXT(B7,"yyyy-mm") -> 2025-01 | P7: =IFERROR(N7/L7,0) -> 0.37373396 | Q7: =IFERROR(L7,0) -> 59.24
A8: =Raw_Data!A8 -> ORD-0331 | B8: =Raw_Data!B8 -> 45659 | C8: =Raw_Data!C8 -> North | D8: =Raw_Data!D8 -> Delhi | E8: =Raw_Data!E8 -> Home & Kitchen | F8: =Raw_Data!F8 -> Water Bottle | G8: =Raw_Data!G8 -> Consumer | H8: =Raw_Data!H8 -> Online | ... N8: =Raw_Data!N8 -> 20.57 | O8: =TEXT(B8,"yyyy-mm") -> 2025-01 | P8: =IFERROR(N8/L8,0) -> 0.26579661 | Q8: =IFERROR(L8,0) -> 77.39
A9: =Raw_Data!A9 -> ORD-0735 | B9: =Raw_Data!B9 -> 45660 | C9: =Raw_Data!C9 -> West | D9: =Raw_Data!D9 -> Ahmedabad | E9: =Raw_Data!E9 -> Home & Kitchen | F9: =Raw_Data!F9 -> Water Bottle | G9: =Raw_Data!G9 -> Corporate | H9: =Raw_Data!H9 -> Marketplace | ... N9: =Raw_Data!N9 -> 4.1 | O9: =TEXT(B9,"yyyy-mm") -> 2025-01 | P9: =IFERROR(N9/L9,0) -> 0.3129771 | Q9: =IFERROR(L9,0) -> 13.1
A10: =Raw_Data!A10 -> ORD-0241 | B10: =Raw_Data!B10 -> 45660 | C10: =Raw_Data!C10 -> South | D10: =Raw_Data!D10 -> Hyderabad | E10: =Raw_Data!E10 -> Furniture | F10: =Raw_Data!F10 -> Standing Desk | G10: =Raw_Data!G10 -> Small Business | H10: =Raw_Data!H10 -> In-Store | ... N10: =Raw_Data!N10 -> 836.44 | O10: =TEXT(B10,"yyyy-mm") -> 2025-01 | P10: =IFERROR(N10/L10,0) -> 0.48024896 | Q10: =IFERROR(L10,0) -> 1741.68
A11: =Raw_Data!A11 -> ORD-0666 | B11: =Raw_Data!B11 -> 45660 | C11: =Raw_Data!C11 -> South | D11: =Raw_Data!D11 -> Bengaluru | E11: =Raw_Data!E11 -> Technology | F11: =Raw_Data!F11 -> Keyboard | G11: =Raw_Data!G11 -> Small Business | H11: =Raw_Data!H11 -> Marketplace | ... N11: =Raw_Data!N11 -> 102.49 | O11: =TEXT(B11,"yyyy-mm") -> 2025-01 | P11: =IFERROR(N11/L11,0) -> 0.34449262 | Q11: =IFERROR(L11,0) -> 297.51
A12: =Raw_Data!A12 -> ORD-0259 | B12: =Raw_Data!B12 -> 45660 | C12: =Raw_Data!C12 -> South | D12: =Raw_Data!D12 -> Bengaluru | E12: =Raw_Data!E12 -> Office Supplies | F12: =Raw_Data!F12 -> Pen Set | G12: =Raw_Data!G12 -> Small Business | H12: =Raw_Data!H12 -> In-Store | ... N12: =Raw_Data!N12 -> 15.45 | O12: =TEXT(B12,"yyyy-mm") -> 2025-01 | P12: =IFERROR(N12/L12,0) -> 0.34680135 | Q12: =IFERROR(L12,0) -> 44.55
A13: =Raw_Data!A13 -> ORD-0361 | B13: =Raw_Data!B13 -> 45660 | C13: =Raw_Data!C13 -> South | D13: =Raw_Data!D13 -> Bengaluru | E13: =Raw_Data!E13 -> Home & Kitchen | F13: =Raw_Data!F13 -> Coffee Maker | G13: =Raw_Data!G13 -> Small Business | H13: =Raw_Data!H13 -> Online | ... N13: =Raw_Data!N13 -> 111.6 | O13: =TEXT(B13,"yyyy-mm") -> 2025-01 | P13: =IFERROR(N13/L13,0) -> 0.34710127 | Q13: =IFERROR(L13,0) -> 321.52
... A1001: =Raw_Data!A1001 -> ORD-0536 | B1001: =Raw_Data!B1001 -> 46022 | C1001: =Raw_Data!C1001 -> South | D1001: =Raw_Data!D1001 -> Bengaluru | E1001: =Raw_Data!E1001 -> Technology | F1001: =Raw_Data!F1001 -> USB Hub | G1001: =Raw_Data!G1001 -> Consumer | H1001: =Raw_Data!H1001 -> Online | ... N1001: =Raw_Data!N1001 -> 38.34 | O1001: =TEXT(B1001,"yyyy-mm") -> 2025-12 | P1001: =IFERROR(N1001/L1001,0) -> 0.37043478 | Q1001: =IFERROR(L1001,0) -> 103.5

Sheet Summary
A1: RETAIL SALES ANALYSIS | TASK 5
A2: Sample synthetic dataset • 1,000 orders • Jan–Dec 2025
A4: Total Sales | B4: =SUM(Working_Analysis!L2:L1001) -> 360030.04 | C4: Total Profit | D4: =SUM(Working_Analysis!N2:N1001) -> 118139.89 | E4: Total Orders | F4: =COUNTA(Working_Analysis!A2:A1001) -> 1000
A6: Units Sold | B6: =SUM(Working_Analysis!I2:I1001) -> 6651 | C6: Average Order Value | D6: =AVERAGE(Working_Analysis!L2:L1001) -> 360.03004 | E6: Profit Margin | F6: =IFERROR(D4/B4,0) -> 0.32813898
A9: Sales by Category | F9: Sales by Region
A10: Category | B10: Sales Revenue | C10: Profit | D10: Orders | F10: Region | G10: Sales Revenue | H10: Profit | I10: Orders
A11: Furniture | B11: =SUMIF(Working_Analysis!E$2:E$1001,A11,Working_Analysis!L$2:L$1001) -> 239796.79 | C11: =SUMIF(Working_Analysis!E$2:E$1001,A11,Working_Analysis!N$2:N$1001) -> 78346.26 | D11: =COUNTIF(Working_Analysis!E$2:E$1001,A11) -> 235 | F11: East | G11: =SUMIF(Working_Analysis!C$2:C$1001,F11,Working_Analysis!L$2:L$1001) -> 102056.35 | H11: =SUMIF(Working_Analysis!C$2:C$1001,F11,Working_Analysis!N$2:N$1001) -> 34091.03 | I11: =COUNTIF(Working_Analysis!C$2:C$1001,F11) -> 241
A12: Home & Kitchen | B12: =SUMIF(Working_Analysis!E$2:E$1001,A12,Working_Analysis!L$2:L$1001) -> 48059.95 | C12: =SUMIF(Working_Analysis!E$2:E$1001,A12,Working_Analysis!N$2:N$1001) -> 16151.55 | D12: =COUNTIF(Working_Analysis!E$2:E$1001,A12) -> 276 | F12: North | G12: =SUMIF(Working_Analysis!C$2:C$1001,F12,Working_Analysis!L$2:L$1001) -> 74480.73 | H12: =SUMIF(Working_Analysis!C$2:C$1001,F12,Working_Analysis!N$2:N$1001) -> 24724.73 | I12: =COUNTIF(Working_Analysis!C$2:C$1001,F12) -> 245
A13: Office Supplies | B13: =SUMIF(Working_Analysis!E$2:E$1001,A13,Working_Analysis!L$2:L$1001) -> 21345.26 | C13: =SUMIF(Working_Analysis!E$2:E$1001,A13,Working_Analysis!N$2:N$1001) -> 7166.12 | D13: =COUNTIF(Working_Analysis!E$2:E$1001,A13) -> 248 | F13: South | G13: =SUMIF(Working_Analysis!C$2:C$1001,F13,Working_Analysis!L$2:L$1001) -> 94009.78 | H13: =SUMIF(Working_Analysis!C$2:C$1001,F13,Working_Analysis!N$2:N$1001) -> 31784.84 | I13: =COUNTIF(Working_Analysis!C$2:C$1001,F13) -> 264
A14: Technology | B14: =SUMIF(Working_Analysis!E$2:E$1001,A14,Working_Analysis!L$2:L$1001) -> 50828.04 | C14: =SUMIF(Working_Analysis!E$2:E$1001,A14,Working_Analysis!N$2:N$1001) -> 16475.96 | D14: =COUNTIF(Working_Analysis!E$2:E$1001,A14) -> 241 | F14: West | G14: =SUMIF(Working_Analysis!C$2:C$1001,F14,Working_Analysis!L$2:L$1001) -> 89483.18 | H14: =SUMIF(Working_Analysis!C$2:C$1001,F14,Working_Analysis!N$2:N$1001) -> 27539.29 | I14: =COUNTIF(Working_Analysis!C$2:C$1001,F14) -> 250
A18: Monthly Sales Trend | F18: Sales by Customer Segment
A19: Month | B19: Sales Revenue | C19: Profit | D19: Orders | F19: Segment | G19: Sales Revenue | H19: Profit | I19: Orders
A20: 2025-01 | B20: =SUMIF(Working_Analysis!O$2:O$1001,A20,Working_Analysis!L$2:L$1001) -> 27488.14 | C20: =SUMIF(Working_Analysis!O$2:O$1001,A20,Working_Analysis!N$2:N$1001) -> 8668.91 | D20: =COUNTIF(Working_Analysis!O$2:O$1001,A20) -> 94 | F20: Consumer | G20: =SUMIF(Working_Analysis!G$2:G$1001,F20,Working_Analysis!L$2:L$1001) -> 122458.87 | H20: =SUMIF(Working_Analysis!G$2:G$1001,F20,Working_Analysis!N$2:N$1001) -> 40100.25 | I20: =COUNTIF(Working_Analysis!G$2:G$1001,F20) -> 355
A21: 2025-02 | B21: =SUMIF(Working_Analysis!O$2:O$1001,A21,Working_Analysis!L$2:L$1001) -> 24909.99 | C21: =SUMIF(Working_Analysis!O$2:O$1001,A21,Working_Analysis!N$2:N$1001) -> 7991.9 | D21: =COUNTIF(Working_Analysis!O$2:O$1001,A21) -> 72 | F21: Corporate | G21: =SUMIF(Working_Analysis!G$2:G$1001,F21,Working_Analysis!L$2:L$1001) -> 111743.24 | H21: =SUMIF(Working_Analysis!G$2:G$1001,F21,Working_Analysis!N$2:N$1001) -> 39271.1 | I21: =COUNTIF(Working_Analysis!G$2:G$1001,F21) -> 321
A22: 2025-03 | B22: =SUMIF(Working_Analysis!O$2:O$1001,A22,Working_Analysis!L$2:L$1001) -> 35838.83 | C22: =SUMIF(Working_Analysis!O$2:O$1001,A22,Working_Analysis!N$2:N$1001) -> 12869.85 | D22: =COUNTIF(Working_Analysis!O$2:O$1001,A22) -> 94 | F22: Small Business | G22: =SUMIF(Working_Analysis!G$2:G$1001,F22,Working_Analysis!L$2:L$1001) -> 125827.93 | H22: =SUMIF(Working_Analysis!G$2:G$1001,F22,Working_Analysis!N$2:N$1001) -> 38768.54 | I22: =COUNTIF(Working_Analysis!G$2:G$1001,F22) -> 324
A23: 2025-04 | B23: =SUMIF(Working_Analysis!O$2:O$1001,A23,Working_Analysis!L$2:L$1001) -> 18171.49 | C23: =SUMIF(Working_Analysis!O$2:O$1001,A23,Working_Analysis!N$2:N$1001) -> 6233.46 | D23: =COUNTIF(Working_Analysis!O$2:O$1001,A23) -> 67
A24: 2025-05 | B24: =SUMIF(Working_Analysis!O$2:O$1001,A24,Working_Analysis!L$2:L$1001) -> 38345.23 | C24: =SUMIF(Working_Analysis!O$2:O$1001,A24,Working_Analysis!N$2:N$1001) -> 12895.67 | D24: =COUNTIF(Working_Analysis!O$2:O$1001,A24) -> 81
A25: 2025-06 | B25: =SUMIF(Working_Analysis!O$2:O$1001,A25,Working_Analysis!L$2:L$1001) -> 38685.19 | C25: =SUMIF(Working_Analysis!O$2:O$1001,A25,Working_Analysis!N$2:N$1001) -> 11888.79 | D25: =COUNTIF(Working_Analysis!O$2:O$1001,A25) -> 89
A26: 2025-07 | B26: =SUMIF(Working_Analysis!O$2:O$1001,A26,Working_Analysis!L$2:L$1001) -> 26137.76 | C26: =SUMIF(Working_Analysis!O$2:O$1001,A26,Working_Analysis!N$2:N$1001) -> 8874.34 | D26: =COUNTIF(Working_Analysis!O$2:O$1001,A26) -> 80
A27: 2025-08 | B27: =SUMIF(Working_Analysis!O$2:O$1001,A27,Working_Analysis!L$2:L$1001) -> 33489.07 | C27: =SUMIF(Working_Analysis!O$2:O$1001,A27,Working_Analysis!N$2:N$1001) -> 11322.9 | D27: =COUNTIF(Working_Analysis!O$2:O$1001,A27) -> 92
A28: 2025-09 | B28: =SUMIF(Working_Analysis!O$2:O$1001,A28,Working_Analysis!L$2:L$1001) -> 27464.99 | C28: =SUMIF(Working_Analysis!O$2:O$1001,A28,Working_Analysis!N$2:N$1001) -> 8152.1 | D28: =COUNTIF(Working_Analysis!O$2:O$1001,A28) -> 77
A29: 2025-10 | B29: =SUMIF(Working_Analysis!O$2:O$1001,A29,Working_Analysis!L$2:L$1001) -> 23636.52 | C29: =SUMIF(Working_Analysis!O$2:O$1001,A29,Working_Analysis!N$2:N$1001) -> 8050.04 | D29: =COUNTIF(Working_Analysis!O$2:O$1001,A29) -> 72
A30: 2025-11 | B30: =SUMIF(Working_Analysis!O$2:O$1001,A30,Working_Analysis!L$2:L$1001) -> 28069.72 | C30: =SUMIF(Working_Analysis!O$2:O$1001,A30,Working_Analysis!N$2:N$1001) -> 9763.99 | D30: =COUNTIF(Working_Analysis!O$2:O$1001,A30) -> 71
A31: 2025-12 | B31: =SUMIF(Working_Analysis!O$2:O$1001,A31,Working_Analysis!L$2:L$1001) -> 37793.11 | C31: =SUMIF(Working_Analysis!O$2:O$1001,A31,Working_Analysis!N$2:N$1001) -> 11427.94 | D31: =COUNTIF(Working_Analysis!O$2:O$1001,A31) -> 111
A33: Sales by Channel
A34: Channel | B34: Sales Revenue | C34: Profit | D34: Orders
A35: In-Store | B35: =SUMIF(Working_Analysis!H$2:H$1001,A35,Working_Analysis!L$2:L$1001) -> 119396.6 | C35: =SUMIF(Working_Analysis!H$2:H$1001,A35,Working_Analysis!N$2:N$1001) -> 40561.82 | D35: =COUNTIF(Working_Analysis!H$2:H$1001,A35) -> 341
A36: Marketplace | B36: =SUMIF(Working_Analysis!H$2:H$1001,A36,Working_Analysis!L$2:L$1001) -> 134062.94 | C36: =SUMIF(Working_Analysis!H$2:H$1001,A36,Working_Analysis!N$2:N$1001) -> 43652.91 | D36: =COUNTIF(Working_Analysis!H$2:H$1001,A36) -> 348
A37: Online | B37: =SUMIF(Working_Analysis!H$2:H$1001,A37,Working_Analysis!L$2:L$1001) -> 106570.5 | C37: =SUMIF(Working_Analysis!H$2:H$1001,A37,Working_Analysis!N$2:N$1001) -> 33925.16 | D37: =COUNTIF(Working_Analysis!H$2:H$1001,A37) -> 311
